jax_datetime/__init__.py
jax_datetime/_src/__init__.py
jax_datetime/_src/core.py
jax_datetime/_src/core_test.py
jax_datetime/_src/numpy_funcs.py
jax_datetime/_src/numpy_funcs_test.py
jax_datetime-0.1.0.dist-info/licenses/LICENSE
jax_datetime-0.1.0.dist-info/METADATA
jax_datetime-0.1.0.dist-info/WHEEL
jax_datetime-0.1.0.dist-info/top_level.txt
jax_datetime-0.1.0.dist-info/RECORD
