Metadata-Version: 2.4
Name: jax-datetime
Version: 0.1.0
Summary: JAX compatible datetime and timedelta types
Author-email: Google LLC <noreply@google.com>
License: 
Requires-Python: >=3.11
License-File: LICENSE
Requires-Dist: jax
Requires-Dist: numpy
Provides-Extra: tests
Requires-Dist: absl-py; extra == "tests"
Requires-Dist: chex; extra == "tests"
Requires-Dist: pytest; extra == "tests"
Dynamic: license-file
